{
  "attempted_candidate": {
    "data": [
      {
        "id": "44c02bce",
        "input": {
          "address": "b8a05af2",
          "balances": {
            "COIN": 1000
          },
          "fee": 0,
          "public_key": "-----BEGIN PUBLIC KEY-----\nMFYwEAYHKoZIzj0CAQYFK4EEAAoDQgAEjKCKXj4/2yIdz0qxhlkT7V2s5KhfZnhK\nkSt+CiKjoFteYC1ofwGM6PjNSGTqBbeK+kESteOVi+DMo/QrAs9WvA==\n-----END PUBLIC KEY-----\n",
          "signature": [
            "55a2c63a6454c3646d6035ecfd83900b48b64956d9cd0f46b44450c94d7621af",
            "f58b30a98ee9ccaad9658d47da75bbb80c46718b68c3dde939702cd40abc92ad"
          ],
          "timestamp": 1759768608
        },
        "metadata": {},
        "output": {
          "5b2a94c2": {
            "COIN": 11
          },
          "b8a05af2": {
            "COIN": 989
          }
        }
      },
      {
        "id": "6c977091",
        "input": {
          "address": "b8a05af2",
          "balances": {
            "COIN": 1000
          },
          "fee": 0,
          "public_key": "-----BEGIN PUBLIC KEY-----\nMFYwEAYHKoZIzj0CAQYFK4EEAAoDQgAEjKCKXj4/2yIdz0qxhlkT7V2s5KhfZnhK\nkSt+CiKjoFteYC1ofwGM6PjNSGTqBbeK+kESteOVi+DMo/QrAs9WvA==\n-----END PUBLIC KEY-----\n",
          "signature": [
            "a8c9001c45f3ec75858231e1debb6a2dc25e58b6fcf4b053fbc2c23fd5984f35",
            "5515d70b285f3942dd3f650f6117d24895dc7dfa1d1fd54a7a5e593f5cf6a2c7"
          ],
          "timestamp": 1759768609
        },
        "metadata": {},
        "output": {
          "5b2a94c2": {
            "COIN": 11
          },
          "b8a05af2": {
            "COIN": 989
          }
        }
      },
      {
        "id": "cb-1759768647",
        "input": {
          "address": "*--official-mining-reward--*"
        },
        "metadata": {
          "miner": "miner-demo-addr"
        },
        "output": {
          "miner-demo-addr": {
            "COIN": 50
          }
        }
      }
    ],
    "difficulty": 3,
    "hash": "13ed5592bb0ffb0574e0df5f98386763485de3f2cd4c1f9d5b2e067ed0330cb7",
    "height": null,
    "last_hash": "genesis_hash",
    "merkle": "9bfb91748d669f6f873d4b96e77f068399a2cefb9e75c62a25b6741c69d74d15",
    "nonce": 8,
    "timestamp": 1759768647
  },
  "note": "aborted by submit-guard (seconds mismatch)"
}